matrix_rdn_det/__init__.py
matrix_rdn_det/matrix_rdn_det.py
matrix_rdn_det-0.0.3.dist-info/LICENSE
matrix_rdn_det-0.0.3.dist-info/METADATA
matrix_rdn_det-0.0.3.dist-info/WHEEL
matrix_rdn_det-0.0.3.dist-info/top_level.txt
matrix_rdn_det-0.0.3.dist-info/RECORD
