Metadata-Version: 2.1
Name: matrix-rdn-det
Version: 0.0.3
License-File: LICENSE
Requires-Dist: numpy
